README
setup.cfg
setup.py
bin/cool_math3
cool_math3/__init__.py
cool_math3/square.py
cool_math3.egg-info/PKG-INFO
cool_math3.egg-info/SOURCES.txt
cool_math3.egg-info/dependency_links.txt
cool_math3.egg-info/requires.txt
cool_math3.egg-info/top_level.txt