Metadata-Version: 1.1
Name: cool-math3
Version: 1.1
Summary: Cool math
Home-page: https://github.com/missingdays/cool_math3
Author: missingdays
Author-email: rebovykin@gmail.com
License: UNKNOWN
Download-URL: https://github.com/missingdays/cool_math3/archive/1.1.tar.gz
Keywords: math
Platform: UNKNOWN
